crabparser-0.1.1.dist-info/METADATA
crabparser-0.1.1.dist-info/WHEEL
crabparser/__init__.py
crabparser/crabparser_rust.abi3.so
crabparser-0.1.1.dist-info/RECORD
