Metadata-Version: 2.4
Name: crabparser
Version: 0.1.1
Classifier: Development Status :: 4 - Beta
Classifier: Intended Audience :: Developers
Classifier: License :: OSI Approved :: MIT License
Classifier: Programming Language :: Python :: 3
Classifier: Programming Language :: Python :: 3.9
Classifier: Programming Language :: Python :: 3.10
Classifier: Programming Language :: Python :: 3.11
Classifier: Programming Language :: Python :: 3.12
Classifier: Programming Language :: Python :: 3.13
Classifier: Programming Language :: Rust
Classifier: Topic :: Text Processing
Classifier: Topic :: Text Processing :: General
Classifier: Topic :: Software Development :: Libraries :: Python Modules
Classifier: Operating System :: OS Independent
Summary: 🦀 Blazingly fast text parsing library with Rust backend - 10x faster than pure Python with support for PDF, DOCX, CSV and 12+ programming languages
Keywords: parser,text,chunk,rust,performance,pdf,docx,csv,semantic-chunking,text-processing,document-parser,code-parser,nlp,multiformat
Author-email: Joao Merlin <loldinis@gmail.com>
License: MIT
Requires-Python: >=3.9
Project-URL: Homepage, https://github.com/Overstrider/CrabParser
Project-URL: Bug Reports, https://github.com/Overstrider/CrabParser/issues
Project-URL: Source, https://github.com/Overstrider/CrabParser
Project-URL: Documentation, https://github.com/Overstrider/CrabParser#readme
